raster_zonal_stats/__init__.py
raster_zonal_stats/raster_zonal_stats.py
raster_zonal_stats-0.1.2.dist-info/LICENSE
raster_zonal_stats-0.1.2.dist-info/METADATA
raster_zonal_stats-0.1.2.dist-info/WHEEL
raster_zonal_stats-0.1.2.dist-info/top_level.txt
raster_zonal_stats-0.1.2.dist-info/RECORD
