Metadata-Version: 2.1
Name: raster-zonal-stats
Version: 0.1.2
Summary: A Python package to retrieve raster values for each pixel of a shapefile.
Requires-Python: >=3.6
License-File: LICENSE
